jetto_mobo/__init__.py
jetto_mobo/acquisition.py
jetto_mobo/inputs.py
jetto_mobo/objectives.py
jetto_mobo/simulation.py
jetto_mobo/surrogate.py
jetto_mobo/utils.py
jetto_mobo-0.1.0.dist-info/LICENSE
jetto_mobo-0.1.0.dist-info/METADATA
jetto_mobo-0.1.0.dist-info/WHEEL
jetto_mobo-0.1.0.dist-info/top_level.txt
jetto_mobo-0.1.0.dist-info/RECORD
